HealthCheck_Pinger/__init__.py
HealthCheck_Pinger/core.py
HealthCheck_Pinger/decorator.py
HealthCheck_Pinger-0.0.6.dist-info/LICENSE
HealthCheck_Pinger-0.0.6.dist-info/METADATA
HealthCheck_Pinger-0.0.6.dist-info/WHEEL
HealthCheck_Pinger-0.0.6.dist-info/top_level.txt
HealthCheck_Pinger-0.0.6.dist-info/RECORD
