Metadata-Version: 2.1
Name: HealthCheck-Pinger
Version: 0.0.6
Summary: easily ping HealthCheck server
Home-page: https://github.com/Gregorek85/HealthCheck_Pinger
Author: Gregorek85
Author-email: grerad@gmail.com
License: MIT
Project-URL: Bug Tracker, https://github.com/Gregorek85/HealthCheck_Pinger/issues
Platform: UNKNOWN
License-File: LICENSE
